{
  "strarray": [
    {
      "name": "device_management_list",
      "value": [
        {
          "value": "电量信息"
        },
        {
          "value": "充电类型"
        },
        {
          "value": "设备信息"
        },
        {
          "value": "RunningLock锁"
        },
        {
          "value": "系统电源管理"
        },
        {
          "value": "设置数据项名称"
        },
        {
          "value": "设备状态感知框架"
        },
        {
          "value": "热管理"
        },
        {
          "value": "USB管理"
        },
        {
          "value": "组合按键"
        },
        {
          "value": "输入设备"
        },
        {
          "value": "输入事件"
        },
        {
          "value": "按键注入"
        },
        {
          "value": "输入监听"
        },
        {
          "value": "键值"
        },
        {
          "value": "按键输入事件"
        },
        {
          "value": "鼠标输入事件"
        },
        {
          "value": "鼠标指针"
        },
        {
          "value": "触摸输入事件"
        }
      ]
    }
  ]
}